inspectomop/VERSION.txt
inspectomop/__init__.py
inspectomop/connection.py
inspectomop/inspector.py
inspectomop/results.py
inspectomop/queries/__init__.py
inspectomop/queries/care_site.py
inspectomop/queries/condition.py
inspectomop/queries/drug.py
inspectomop/queries/general.py
inspectomop/queries/observation.py
inspectomop/queries/payer_plan.py
inspectomop/queries/person.py
inspectomop/queries/procedure.py
inspectomop/test/__init__.py
inspectomop/test/test_connection_url.py
inspectomop/test/test_inspector.py
inspectomop/test/tiny_omop_test.sqlite3
inspectomop-0.2.2.dist-info/LICENSE
inspectomop-0.2.2.dist-info/METADATA
inspectomop-0.2.2.dist-info/WHEEL
inspectomop-0.2.2.dist-info/top_level.txt
inspectomop-0.2.2.dist-info/RECORD
