Metadata-Version: 2.1
Name: inspectomop
Version: 0.2.2
Summary: Database query tool for the OMOP Common Data Model
Author-email: Jonathan Badger <jonathancbadger@gmail.com>
License: GNU AFFERO GENERAL PUBLIC LICENSE
Project-URL: Documentation, https://inpsectomop.readthedocs.io/en/master/
Project-URL: Repository, https://github.com/jbadger3/inspectomop
Keywords: data science,healthcare,ehr,OMOP,OHDSI,cdm
Classifier: Programming Language :: Python :: 3
Classifier: Operating System :: OS Independent
Classifier: License :: OSI Approved :: GNU Affero General Public License v3
Classifier: Development Status :: 4 - Beta
Requires-Python: >=3.8
License-File: LICENSE
Requires-Dist: sqlalchemy >=2.0
Requires-Dist: pandas
